{"pz1+xRE774xzho6sLgOjYw==":"301.jpg","Rw154wr9yGNMaJAKpAL/fQ==":"302.jpg","CvyEfhk4WyPEeGPlrWLlvA==":"303.jpg","Q1bJppN69sfORPHQPOgjhw==":"304.jpg","bQfFnkVhRu/+Y8wY08t3Dw==":"305.jpg","FFc5FLjiJGNItxPEh4jzAw==":"305.jpeg","duRTq5YH9XNUeaWWTWynkA==":"305-1.jpeg","OT1MO/pqkrM5cAjqKFCWcw==":"305-2.jpeg","ySCnmDUQzYRc9J8xciWD/A==":"305-3.jpeg","vkLMsYTmukah/PfB4/3QBg==":"306.jpg","4vHnoBYowURrLkTOswVWPA==":"306.jpeg","XN6xdPrphtlbOgSoNI80ug==":"306-1.jpeg","0s8eHQlqLV8tL9xs20ti7w==":"307.jpg","fJ0QzqfFcXyzjmYoUx11uA==":"308.jpg","u4emsNB4AMyUYEJ1Qez9kw==":"308.jpeg","xM3smV0BOcVBtffc+036Eg==":"309.jpg","RioyTi/K/TFIvm+j/l7DrQ==":"310.jpg","oOVcDWxB/l7Nny3ZIi2ZSg==":"311.jpg","fSAy4Z8A75oAPxgyICiADw==":"pexels-sound-on-3394650.jpg","PJcyM87FH0GojiQ1LX1lVQ==":"311-1.jpg","MN6cifIPx6/B85ca6T21bg==":"314.jpg","SUhRSWoaY7Sshr37X9kV2A==":"ammar-abu-zaid-ap8lq6de8fa-unsplash.jpg","uweaakiMeCz+RDEtpxsZag==":"315.jpg","YCnZrbjLEkgp580tLVuMww==":"309-561x374.jpg","dHrjeNdexbs63K+KJVchmA==":"310-561x701.jpg","gNSTrZstg0PMN8Oo6V4RnQ==":"3011-1200x673.jpg","rllVDUoW/5R8EqVZvA1Iag==":"303-1200x800.jpg","PKFbQm13L7EmQ+cCrT07pw==":"304-1200x800.jpg","YbPR2rv0FZfvW9nmp7U0sw==":"037-1200x800.jpg","Oo+/Ke9PIWXJppWSfoWPJw==":"302-1200x675.jpg","d+GzzZ5F7TuOxJv6LQRabw==":"309-500x333.jpg","hHLVIxxC5Fk8hZWpXFjP8w==":"310-500x625.jpg","vcOQ4sBqYhZRFEgdQHl+ow==":"317-500x625.jpg","88lpO2qrfVCwAEmdX2zdAw==":"313-500x500.jpg","l/8YmOwnX51CFku87WTKdw==":"311-500x331.jpg","UjM/o1TGUSabw1/kK6Wqhw==":"314-500x333.jpg","Nb7bakhzOVGQYd0rGZ0TbQ==":"316-500x350.jpg","f5b+XIF6xfMCsAwEFVxGyQ==":"315-500x333.jpg","0PCJP9I5V3hT3idLgRFI1Q==":"305-1200x805.jpeg","rnN0FCQU/j3IESPSSBeafQ==":"306-1200x1780.jpeg","BVtqi8ch7jSXhs1uPsFb1g==":"306-1-1200x1780.jpeg","9zwzUszBA8NKrmDwcNgtvg==":"307-1200x800.jpg","yW6vF8AZfL4CsurpwXeJ+g==":"308-1200x798.jpg","YD/muPNllywxZqAEr+1EYg==":"electronic-device-1.png","6ZXrxVC4MAB7vQHIMLZv0w==":"image1.jpg","s20uKEC57Bm6Io9UyQgV/A==":"image10.jpg","ZAC8VV+oq5se+ZyNR6EZMg==":"image7.jpg","g7ddc3kN6k7s2Ae74x+jMA==":"image3.jpg","Vm51W4aSvgGhZlM3mF0Y6A==":"background1.jpg","oQkeWhmFnYbufC99j1R+aA==":"swoim%20szlakiem%20main%20background-1920x1028.jpg","7Z3+UmnHB5kFPL+dR8CZhw==":"logo%20swoim%20szlakiem-180x180.png","5KQtBXt3x5fyNoR2Q73wjg==":"1_obraz_1tip-photoroom(1)-360x505.jpg","EUeNQZ+fwdUHDpV1SCI3pQ==":"nx7000wst%C4%99p-new-360x202.png","ET8cH8wXbM82PeVlUi2lyA==":"nandi-new-360x640.png","I2CJV0hLoqd113IhHR+zlA==":"dd44b361-7caa-4634-ae2c-04a806cfac48_i-nandme-nx9000-b12-czarny-koncowki-12szt.webp","YdJYNChZyAx7s6G6hcv3nw==":"background1-1.jpg","TildJaDCuChKqCV6MO9hGg==":"card2.jpg","WRaEg78Xyl+G3pniosmzHg==":"mbr-2.jpeg","8svCvqX4xbuJ5bNT7MmBnQ==":"mbr-1.jpeg","Ix+W8BcI/GlWknNIzPsMKg==":"background3.jpg","6jxu8lCJA0cydJMkVQx1QQ==":"background1-2.jpg","XP8qPw3tgRdeixdEdTge3A==":"mbr-1920x1283.jpg","waRTo7Zg6/OSc+RVDrebcA==":"mbr-1920x1224.jpg","wZwcUMa2zYmmyyx2NkzWZA==":"mbr-1920x1307.jpg","bAYBO4weoxIeVI65X+DjKA==":"mbr-1920x1282.jpg","7bgU/3K8iHSbibrhoq8I1w==":"mbr-1920x1280.jpg","uYlv2DZZ9AyfUlKccNknKw==":"mbr-1920x1080.jpg","/ZJ0U5Y56RnDCIlkCyXW0Q==":"stylo-360x234.png","nxjFWbjbbx7/kogzJsHySg==":"stylo-1-360x234.png","pGgPythKaX00LnRgJPvivQ==":"stylo-2-360x234.png","T03iGfmVVIGoeAbne9C5NQ==":"stylo-3-360x234.png","fOiV6nlujOTB/2BI50lL2A==":"stylo-4-360x234.png","ONiMKreHvN0VpmgipJNoww==":"stylo-5-360x234.png","l389wo+Stww0N8Uljn+2oA==":"stylo-6-360x234.png","DEe1z2/RB3xxHvxdBMtbLA==":"stylo-7-360x234.png","cw3QUiykkyJ8E3P3Qgk+9w==":"skiba-360x234.png","D9XvA7Q+QtaFLYNsHJwG/g==":"skiba-1-360x234.png","z5MmxPq6iWlpmCwrRL4clA==":"skiba-2-360x234.png","ujuJd/WSfCsZhD1p+VAqSA==":"skiba-3-360x234.png","ETelNHJ6HAwm/gCBqulCYg==":"skiba-4-360x234.png","Y3i8loI74fYQShr5a9V+0g==":"skiba-5-360x234.png","q62BRWgkNVVcPXugEusEyw==":"skiba-6-360x234.png","R8osHiIF0O9PBfPalvXDZA==":"skiba-7-360x234.png","tt+hyhII6AWwenPi1+qGJQ==":"skiba-photoroom-360x234.jpg","+s7LH8lxKDvt5pwsG5cWQg==":"skiba-photoroom(1)-360x234.jpg","h5OWeWEHvvzG2V2Ql8Io3g==":"skiba-photoroom(2)-360x234.jpg","2iQGBwsgRCEdsdeMf4C4vQ==":"skiba-8-360x234.png","OwA0GkeL/Yd+2OzosjJ/Pw==":"skiba-9-360x234.png","C1rB/iAGHShXrFLcMlVcFg==":"skiba-10-360x234.png","654hCGOUezmGa0s5fH0YPA==":"skiba-11-360x234.png","t9rk7RDulQkTtnX3EhUALQ==":"skiba-photoroom(3)-1000x650.jpg","26Qod0FlI01fIExMTDhD5g==":"skiba-12-360x234.png","Ohi2SruUsIMaOU5PcGZnKA==":"skiba-13-360x234.png","SXr3CbUMah/P6tlj592uog==":"skiba-14-360x234.png","xzULUhmxuVJlIYDAOAbhGg==":"skiba-15-360x234.png","RRSkEwNHMOnynv21EZ70sA==":"tyyt-photoroom-360x234.jpg","ImtcWfdTrq51Sna/nqef5A==":"ca%C5%82y%20nandme-new-360x234.jpg","LL9rTzlHUxyc9/ZfnNbBxw==":"background1-3.jpg","tG8wCuG0FDr0BpDBYzEtSg==":"skiba-photoroom(4)-1000x650.jpg","rKmviKYKbPT0YkYk143ZDg==":"ewa_ufo-1920x1280.png","AQdbWYPeryqwnneP8WlQ+A==":"ufo_ewa-1920x1280.jpg","8qOvdKByycYHhvMAho7yeg==":"ufo_ewa-1-1920x1280.jpg","4ZA8CA11FgBoLJqf6PQstw==":"ewa_ufo-1-1920x1280.png","iMhM/iW/kvmRfqpd1IA5nw==":"ewa_ufo-2-1920x1280.png","IX3jRnGDpTbc0BcypTccQw==":"ewa_ufo-3-1920x1280.png","Lm3uNkwjCr/XcP4WmkIDeg==":"ufo_ewa-2-1920x1280.jpg","BPcPyHYIdXb/oBz6bXWxkw==":"ewa_ufo-4-1920x1280.png","0I7ZVXYXgoy2khtDr+7rDQ==":"ewa_ufo-5-1920x1280.png","vWz8hrc0bpyljsAzB8p++A==":"ufo_ewa-3-1920x1280.jpg","ApA2Ttws8FavaK8V3QCcbQ==":"ufo_ewa-4-1920x1280.jpg","gg+sXBg0ejzB+GdwAC/WbQ==":"ufo_ewa-5-1920x1280.jpg","H1rzNnW2mQ9EuBy1CAVgtQ==":"ufo_ewa-6-1920x1280.jpg","XP2528RLAb0CG0zwS+sjCw==":"ewa_ufo-6-1920x1280.png","j8s1pTyZsNzO0eIF+77oXA==":"ufo_ewa-7-1920x1280.jpg","q3iNQKKEgtf1tdCD2CiOmQ==":"ufo_ewa-8-1920x1280.jpg","XfabkdCqCI7c6Hqt7wl+Zw==":"nandme_halloween-1000x650.jpg","z0HFYJgyuj8MlcwvGAABBQ==":"nandme_halloween-new-2000x1300.jpg","8frCUmCPMcVQ7SeJfXeEPg==":"skiba-photoroom(5)-1000x650.jpg","CKfhJC57zU/XSUzt1eb/lQ==":"skiba-photoroom(6)-1000x650.jpg","px+WIGqP53paVzvZHQs7lg==":"skiba-photoroom(5)-1000x650.jpeg","+V1Ng4ia40FDov97ZoNJwQ==":"skiba-photoroom(8)-1000x650.jpg","JITz3Zvf/+vP/bS0+poUOw==":"skiba-photoroom(10)-1600x1600.jpg","BAQCyEU66tZmnJN0svxIhQ==":"skiba-photoroom(9)-1000x650.jpg","Fh9xDQU0IFxD8DeusG7IPQ==":"skiba-photoroom(7)-1000x650.jpg","awxbRg9lgWU/LPV47WoWhw==":"ufo-photoroom-1000x650.jpg","Q6pzZiSrjEzRaU0vLA2vDQ==":"ufo-photoroom(1)-1000x650.jpg","Lmed2DyhsO5ync0o1eUcJQ==":"ufo-photoroom(3)-1000x650.jpg","A/HnUk3s5xEb6ZRSg3/DfQ==":"zkzzk-1000x650.png","JKfAYxR3UQr26BiBE7bJPw==":"zkzzk-new-2000x1300.png","+Nl+s86QYxgJMpGFOiEMaQ==":"zkzzk-1-1000x650.png","ApMy6e9xxbYYKthoqQ2jcw==":"skiba-photoroom(9)-1-1000x650.jpg","NNekMsJanVyullWZxWWOCA==":"skiba-photoroom(9)-2-1000x650.jpg","F5U60jVapUFWIZ4v9JLEGQ==":"zkzzk-2-1000x650.png","mW5/x9A4Dvb3s0ebklmPBA==":"ufo-photoroom(6)-1000x650.jpg","DWdejQ2quRO0yW2cgW9b1g==":"ufo-photoroom(5)-1000x650.jpg","QhVsroxe77nev4gupB54bw==":"przezroczysedynie-1000x650.png","REksG/iC4DQScYmKVXGKNg==":"przezroczysedynie-1375x894.png","HrG5zT+ihn8R936z0Kky+g==":"przezroczysedynie-2000x1300.png","TDGIW2SR2+EgP/BI4hGR3g==":"przezroczysedynie-1500x975.png","YVWMZpR/rezjQ1sUAsJDjg==":"przezroczysedynie-1125x731.png","RS1tll5K/vNbzXbah1u6KQ==":"loliu-2000x1300.png","14p21fnpmFQRsWQ7/HHcNw==":"123433-photoroom-1000x650.jpg","RZhkGQ4Q2pCAXxVabpT6cg==":"forma-1000x650.png","8tZ2lv1uY2EcaI0vzs3tJg==":"forma-2000x1300.png","Q8cNpoEWbnVsdY514JnScA==":"forma_easy-resize.com-2000x1300.jpg","mJ+gdI87fYSEZnhn7P3dKQ==":"halloween_logo_nandme-1000x650.png","vBejbwyoxBzHYz9JX8Jh0A==":"halloween_logo_nandme-2000x1300.png","xILrhXj6slDihmGIsIGMFA==":"ewa_logo_strona-1920x1280.png","T3MFTnN+6F2AiLQFyKhPsA==":"ewa__logo_produktowe-1920x1280.jpg","zlE9DTOhw2zY22e3QAFotA==":"ewa__logo_produktowe-1-1920x1280.jpg","dChfq1gahuBedc/rAfM2vQ==":"v11-360x349.png","5nIY+REfUzEfYZXA4Z3JKA==":"v11-1-360x349.png","kyflYILHFY8uoOG2KQaROg==":"v11-2-360x349.png","8FLkwhXubLBSgNEBlVJZdw==":"ewa_earphone_buds-360x349.png","+WfSzPGwZJ+oSyhlh0eEHw==":"ewa_earphone_buds-1-360x349.png","TRuktvJUYMULlXq6sHV3Mw==":"ewa_earphone_buds-2-360x349.png","rwgSHm8kFg1yzp5mQiUWtg==":"ewa_earphone_buds-3-360x349.png","OhKLBhPOFvg9bTx9n81PVQ==":"ewa_earphone_buds-4-360x349.png","4wbBlfEid6RDhqvNKQZgzg==":"ewa_earphone_buds-5-360x349.png","aQ+Y+mPX/0I1O0MALJ0QRg==":"ewa_earphone_buds-photoroom-360x349.jpg","4xO/CouEPq9HeitAdHX8ag==":"ewalogo-new-312x200.png","miIsPbRKOUF74EsEa6pLpQ==":"mbr-1920x1411.jpg","jBX8H44lKkN7xtMx5XQrgg==":"nandme_wampir-2000x1334.png","gy6DCHEXfld3M/kw3ST7cA==":"mojet-1920x1280.jpg","V1v6lXkTJ3JSIad8lTVAWw==":"wampt-1920x1280.png","S9LYRE1qOnEl6hkoJ/N9KQ==":"wampt-1-1920x1280.png","i4BJTiu/a9D+5jg1aLqm+Q==":"wampt-1920x1221.png","0jbkDHfAfGw0nQDnv+Po2A==":"wampt-2-1920x1280.png","qtIseyAe+z/AI0LfWR2EdQ==":"wamt2-1920x1221.jpg","Ue2HnCNXoBaRq0wOTIdaHA==":"wampt-3-1920x1280.png","ZMUg2Ii7c5SNLcrH0fvsuA==":"wampt-new-2000x1334.png","K5f2ZItY5SdxBwHbwtIxAA==":"wamt2-1920x1280.jpg","SnSCp9GhlgrnrkZvLyGzvg==":"wamt2-1-1920x1280.jpg","WKGEZ2FvIXEba6oUUGhZoA==":"wamt2-2-1920x1280.jpg","FaqKHcybKe7WFI4Lm3APwA==":"wamt2-3-1920x1280.jpg","hN6dtSnajFF/dZ4xPBL7XA==":"wamt2-4-1920x1280.jpg","2wck5/D0iXtFDivXMs17dw==":"wamt2-5-1920x1280.jpg","oJO6DI41hsiL/9fVfeIgjQ==":"wamt2-6-1920x1280.jpg","YudobRE8xS32saFwbIuwlw==":"wamt2-7-1920x1280.jpg","2/9CGGqiVfNFpbw+LPsZ4g==":"wamt2-8-1920x1280.jpg","GDQHSMOfsbkBh2jGwGn0Sg==":"wamt2-2000x1333.jpg","YYapt2u31kG31Mm+tFnxDg==":"wamt2-1-2000x1333.jpg","UFeAMsJv5/oPeKXfzgyY9A==":"wamt2-new-2000x1334.jpg","eUKO/BoebXXCzx1IWdOs3w==":"nandme%20wampir-2000x1333.jpg","+1NlKO0yvbcZI4vA6X5a6Q==":"nandme-269x261.png","6H4ExGXUuZuQYvySmoIppw==":"nandme-1-269x261.png","6nscBnl4YTr9eYadUj84Dw==":"nandme-2-269x261.png","E/Uzjf/phzDxqluHNb40xQ==":"nandme%20wampir-new-2000x1333.jpg","qe8uUwj6W6jqTWg9xqIUAA==":"banner_900x.webp","1CfmpHIk6ZkYvNFFrZApyw==":"banner_900x-1.webp","Qs7Omy4ww+DhvBrNxP5S2Q==":"nandme_banner-705x684.png","eGggtpaHcJKPjlRX3iHdsQ==":"ewa_banner-705x684.png","XLHDWt9swd81Z4rjrm5qKQ==":"ewa_banner-1-705x684.png","OKx+N9BXl/3G4AVjUZe+wQ==":"nandme_banner-1-705x684.png","X9cPUbD98Z3DJvu1c/OTgQ==":"banner_akcesoria-photoroom-705x684.jpg","sVV6lQHG+mAL4a0lIM2YuQ==":"banner_akcesoria-photoroom(1)-705x684.jpg","fTiB8mjJTp3djpGk7UVJLQ==":"nandme%20wampir-1920x1280.jpg","KYtBbSayAG7QkoQfh3qvSw==":"szczoteczka_tlo-958x929.jpg","eJq730YvMMyk13UCLqJCuA==":"szczoteczka_tlo-1000x970.jpg","e/SK2KVDEqZpxJJMAvUovg==":"lista_szczoteczki-1000x970.png","vSkvVSPYlOJhgjXtvo3eJg==":"lista_szczoteczki-1-1000x970.png","3e3IAntWNp65dYtlrQ90sw==":"lista_ko%C5%83c%C3%93wki-1000x970.png","YiErK6MljsHo0vGSgCmFcA==":"lista_uchwyt_do_szczoteczki-1000x970.png","7EAgTIK0KlJproHY18n9pA==":"lista_uchwyt_na_szczoteczki-1000x970.jpg","8+LS/5LDsFc7dF8aJN5dtw==":"lista_s%C5%81uchawki-1000x970.png","tcB7KhzS6k7+p6c94fAsnw==":"mbr-1920x1307.jpeg","JvIH9EX/mTJ1uqrwX25DMg==":"mbr-1-1920x1307.jpeg","etZfR3m4lc6qSnvcLMqeLA==":"mbr-2-1920x1307.jpeg","UT9YrZeCcW6lYEviJeN5iw==":"do%20stempla-1700x1274.png","iro37z+7UXrgDeHRR1wWGw==":"russia-938x724.png","2wUMu6vOmkg3WFNIcQr12g==":"russia-1-938x724.png","89QKAFaKtmqzYERFp8HZAg==":"russia-2-938x724.png","q9x6flm4fQS4n/VSOA5A0Q==":"russia-3-938x724.png","nf62HUNqPwWUV122Q/6t2w==":"305-928x716.jpg","WnIUDHFjLZ8U+LNfwr6Epg==":"russia-4-938x724.png","Mc+aHH53UgBIgMT0Gu83Mg==":"russia-5-938x724.png","mRvRBrB00DR+gvp71pHv9w==":"russia-6-938x724.png","WhLKv4mvBPI9vmouYGfwTQ==":"russia-583x450.png","0Uh3ivsWkGS+2GTbB19XdA==":"russia-7-938x724.png","y5SMiQ2m5d9Ui0xfWjJJTA==":"russia-8-938x724.png","xYYwWnkJ8+GMROhOgqa+MQ==":"russia1-938x724.png","3DeUKAdnbQU+HUxuGvMHvg==":"russia1-1-938x724.png","RU7QGwhTg8QxFqn+1WfxWQ==":"russia1-583x450.png","GqOUlT/jOmrIpTDaU6J0MQ==":"russia1-2-938x724.png","/cuWdTJIdCtY/RFfES40dQ==":"russia1-3-938x724.png","P4Jyvp8WKaLvSkbqRRjpJw==":"russia1-1-583x450.png","ELky50HbQSL1HpUNuGC7Ww==":"russia1-2-583x450.png","Z5mDZjCs7iIEGJg0Y0moFg==":"russia1-4-938x724.png","Ri3tYj9Pls+3MTRU/afi8w==":"russia1-5-938x724.png","wx6xKNf4laTvFrNAFGaNTA==":"russia1-6-938x724.png","tZZqJSU2bOSlOMCiPkFPkw==":"russia2-938x724.png","vf4O6rpd4OS5gKXhRtLWSA==":"russia2-1-938x724.png","9+eGCWBjPCiMxUvK7lYqRg==":"russia2-2-938x724.png","MtBo9KQz85PZkmFHrQJH/A==":"russia3-938x724.png","BFgmFHyJVctUslmU6EYTPA==":"russia4-938x724.png","LNobBn8ho9ygUMjSyEX7Ng==":"nx7000%20ad%20logo1-938x724.png","EqPR79VlvBhRj043UgZeZg==":"nx8000%20ad%20logo2-938x724.png","JHrcFp342bbuujYdSNQPaw==":"nx9000%20ad%20logo3-938x724.png","/AimXtGiTLijUqmA0fYk1g==":"t-300%20s%C5%82uchawki%20ad%20logo4-938x724.png","2OeyUZrRzWb7zQ4HOjLcaA==":"uvc%20rabbit-938x724.png","88symm86KO4GvhDpE4f8+A==":"nx7000%20category-500x333.png","qL5tiCKp/V7V8GTRqdileg==":"swoim%20szlakiem%20category.svg","Fl4kkpP9w3PpfagGHvcQqA==":"nx7000%20category-500x333.png","Xcuk0f6t/zqUpmO8SVnRBw==":"nx7000%20category-new-561x374.png","zeFbnQH0olzlO65aj79u1g==":"swoim%20szlakiem%20category.svg","wjc2XptczxCHPGtbLlLuHw==":"nx7000%20category.svg","UjxrNZ1u42hsMX0ic40fmw==":"nx7000%20category.svg","pKFAtNq2l/i6JZdJifx5Mw==":"nx7000%20category.svg","O0tDxk+1opPJvlWsIvmTyg==":"nx7000%20category.svg","B37HBuqnfYjkpc6bnRia8w==":"nx7000%20category.svg","doviIUV3i4qs4eHSpt7kTQ==":"nx7000%20category.svg","iaaHJ4c+kyl6hyE/bFsOAw==":"nx7000%20category.svg","qf3+cmY+H0F4wMnVHeqUuQ==":"nx7000%20category.svg","pRr+zuj5hDMMjj2v+hg5Xg==":"nx7000%20category.svg","uvnaz0J5kGXnnpyEv1mL9w==":"nx7000%20category.svg","D1VP9c72xhA+oV6U4f5mDw==":"nx7000%20category.svg","pfR3WIBL1R03ldubNzrbcQ==":"nx7000%20category-500x333.png","XzR/rHGw5FlFz5DArXzm5Q==":"nx7000%20category.svg","eRrp/VXiRBkSnNbaw96Mqg==":"nx7000%20category.svg","kp1NmenuE4kedRpKKj/uag==":"nx7000%20category.svg","424QBf/4O84emc4FM9BMqQ==":"nx7000%20category.svg","YRkpOMaMrUq/NDLjl/SoFg==":"nx7000%20category.svg","95tltCcrMEvXWstC0yD5ow==":"lojol-photoroom-500x333.png","cl4VHlOMM9pQ6itJTH3Uhg==":"lojol-photoroom-new-561x374.png","lDkqgjk+jPNebDZmsVoDQg==":"lojol1-photoroom%20(1)-500x333.png","qIbM1ALM36FYy088E8cmeQ==":"lojol2-photoroom-500x333.png","v5qkcwvt55q110tDhiK2Zw==":"lojol2-photoroom%20(2)-500x333.png","JH+KDv2NC66/yOaNO/JlYA==":"lojol2-photoroom%20(1)-500x333.png","Val66gRRzoaQ/YI4jVU84g==":"lojol3-photoroom%20(4)-500x333.png","nyvwGdqTOFlJshuuTWYMNA==":"lojol5-photoroom-500x333.png","OQfCVS1X5xxOUwsgItv9GQ==":"lojo5-500x333.png","yi1RnWWHJekr0yTfXmDFEg==":"lojo5-1-500x333.png","2X/uqExHcxMKif8wei01pg==":"lojo5-2-500x333.png","LBLKtHmSwv6QYywwmhtQrg==":"lojo6-500x333.png","wSUyp1Z7V6grQ0aX86gGeQ==":"lojo6-1-500x333.png","1naTZCO/iJq1n7l7LhLnEw==":"lojo7-500x333.png","S3wBLDlOXaWit6BsNSJrvQ==":"lojo8-500x333.png","V1nXqyLI+K+z7qhBubCc9Q==":"lojo7-1-500x333.png","YqxxBEJTfno4KeNOVU7E0A==":"lojo8-1-500x333.png","rEGIwhBWlerV/fa/UV3vpw==":"lojo8-photoroom-500x333.png","SegZNvSvwIa9PZqXpCT1CQ==":"1na100-500x333.png","LHStCPVi5le2jKMQzB7ZHg==":"1na100-1-500x333.png","CifpTQs9d2BLfzc3l6OU1g==":"1na100-2-500x333.png","0lHFcMtT5wklkKCQuK0ucg==":"lojo8-2-500x333.png","c+PYkldTeJ6Kp8RaadBvRg==":"lojo8-3-500x333.png","v6po9ZuPJvg7xuX4er+Mbg==":"lojo8-4-500x333.png","fik1K6lcWpNYB75yT0vIWg==":"1na100-3-500x333.png","Xz+L5WVw1B1AO5FT7hrCVA==":"lojo6-2-500x333.png","M7m8Su1v76TaRiSNz/21jQ==":"lojo5-3-500x333.png","1aTfi5TTjFRrPbPvpTvm5g==":"lojo6-3-500x333.png","6SDu/qKSXZS+Qgr/c0ckYQ==":"lojo5-photoroom-500x333.png","HOkU4eN/tvPGFhGe9TcWMw==":"lojo6-photoroom%20(1)-500x333.png","tuKkmax9o/9PoPbFOdIE/A==":"lojo6-photoroom%20(2)-500x333.png","35jFuwEs51j65ehRI9yUmg==":"lojo6-photoroom%20(4)-500x333.png","dczvdPmXZ+Ja+3XkopA+7g==":"lojo6-photoroom%20(5)-500x333.png","4A0dfe8Lkd/fxDnR7VjfUQ==":"banner%20klasyczna%20moc-269x106.png","US1e65/ZRkZhPiCKqhrrig==":"banner%20klasyczna%20moc-246x95.png","4xRy0PbilIjGbKHGPw9Iyg==":"nandme-2-202x79.png","a+kXJHA59/QMDQLc8cUu+A==":"nandme-3-202x79.png","ZO88PhG9i4TWeP1vxczsvw==":"nandme%20professional-202x79.png","vKeM+ASj6RY0javKNq1nyA==":"nandme%20professional-202x79.png","GC+VpEHRK/+ovaP01p9nYQ==":"nandme%20pro%20ellegance-202x79.png","tr+tIjgB95K8gPtXbOYKOQ==":"nandme%20pro%20ellegance-202x79.png","UeU11TGuIKAi2sT0pVuOXg==":"sterylizator%20uvc%20banner-202x79.png","naaRG4bcSYwJCr27nyXh9Q==":"nandme%20szczoteczki-705x684.png","+S+O88mu2/hnw2emdzq7IA==":"ewa%20sprz%C4%99t%20audio-705x684.png","T9zcO1/B1j9DQnJml25X3A==":"ewa%20sprz%C4%99t%20audio-705x684.png","+APwG5lS/97J/rFANSjBcg==":"features19.jpg","/B1CB51G6L+hENLAFtO1EQ==":"background2.jpg","zGYagyXb5Njt+strnMcsww==":"background3-1.jpg","NzfZd/a5M7t391jtJ7x/+w==":"features2.svg","BuKh+InBF+p4fWefZzwt8A==":"background2-1.jpg","2owg/3rfJHR+45XZYHkS8Q==":"004.jpg","Mn7cJHd7tlmAXXe9WEEUPw==":"203-1.jpg","FJBVbCPYtvGTfYOw7PDPDw==":"mbr-1920x960.jpg","CriX9dP2MoRrZOOyg1mLjg==":"mbr-1920x1187.png","pmFs438eyQchauWBzZigaQ==":"mbr-1920x757.jpg","lWt9oAz5QAkSShBwa+8/NQ==":"mbr-1920x1303.jpg","BK018Gxv0SowzhHZJRyZGg==":"mbr-1-1920x1080.jpg","7oPQY8/h2JJdowrmLA0Svw==":"mbr-1-1920x1280.jpg","kCjz3jSSlEYm76VXt6kmQQ==":"mbr-2-1920x1280.jpg","mMUevWKGBqGQCV8U0DmXvg==":"mbr-1920x1082.jpg","kffjNHsot7hEfvaFR5aujQ==":"mbr-3-1920x1280.jpg","htEu8c9Ww00KS391Cfg+jQ==":"mbr-1920x1275.jpg","NzHLY1vp1rCyk6+nz8DaVw==":"mbr-1920x1920.png","B0x0vXhwsuocubpqC8fW9g==":"mbr-4-1920x1280.jpg","v5OfvRT/M8KdG8sg/jXXzA==":"mbr-1920x1274.jpg","pvDAtAftdcmtp1jFkqJMkw==":"mbr-5-1920x1280.jpg","Rbj+8ZLdDJCe4Yzyx5ne6A==":"mbr-1920x1278.jpg","JW2UQudEkIt+AZ6ncFG7cQ==":"mbr-1920x1281.jpg","7OJUUYzQIJhChWy4SvaEyQ==":"mbr-6-1920x1280.jpg","bCSOI8e95iLOhkLwINSJmQ==":"mbr-7-1920x1280.jpg","X3wge5wZYkPSJEq0pXGmGA==":"mbr-8-1920x1280.jpg","wYv0I82AuQP+zz01i33+xw==":"mbr-9-1920x1280.jpg","vLb7Wbguk1huiID8GmSMFA==":"mbr-2-1920x1080.jpg","FvsH2TaWy1v4Jrfo2HHLFA==":"mbr-1920x1211.png","AiBgFmC5J44PvNnMDGNhhg==":"features1.jpg","eYUe13KMwNYkfA7Gs9+lTg==":"background1-4.jpg","jyMuvHCyT/EPYz/miRlUOw==":"background2-2.jpg","diTGClAIN9z4hd6ddRzyyw==":"background3-2.jpg","uk4KS12bisTwDIKQljkLzA==":"dots.svg","mRXqFBmVQmbKk1ZkdQjU+Q==":"background.jpg","K4WkO3JD2x6JgFsq5hbcaA==":"gallery3.jpg","KtQx7Iy+d6koUYxGejXTlg==":"gallery1.jpg","WXREoEOkuwaQjoo/pPAcLw==":"background3-3.jpg","c7AAd0vh3UUQ6GEMLWkkXg==":"gallery2.jpg","rCsu4Em91lneGR3KUG+8sQ==":"mbr-10.jpg","lS14TTYYKa4wXGdCc/JoDw==":"mbr-8.jpg","m8emEjxrYtGfi/9XHQbLIQ==":"mbr-9.jpg","2gGKEm+fOes3sTb1kqytVA==":"mbr-7.jpg","2lBJQndLmW9/lIFf/EdC1w==":"build.svg","oRykAiO0rUD++7AmPeEwUg==":"bg1.jpg","pHZYHp2/DvsPLKTVWFF19A==":"1-1-708x472.jpg","QtnTtn71j/x/tE2cez33Rg==":"mbr-1-861x574.jpg","kxmuZOg1ftjqXldQmiZwnA==":"graphic3.jpg","7ux0OjKw+5S8rIpIjS9CRw==":"mbr-3.jpeg","VkdDgkIK/YrTAbuZ5MRiKQ==":"graphic2.jpeg","u08J8ZQRaNzROtzDoRWgTQ==":"mbr.jpeg","H3Rz2BIKmPgtMqSzMTAXmw==":"mbr-10-1920x1280.jpg","gNv/M7DqiWiBTJNwk3hcfA==":"conference1.jpg","UiHXKNbTr+fSzEAYvSg3lA==":"conference28-1920.jpg","r5VkD7z9g8uiaooSx58X8g==":"mbr-1009x673.png","RQFX80JL8HO6B2mYYPAX1g==":"mbr-1009x1253.png","krx1tlFCnY3fUMnCi3ZRbg==":"o%20nas%20t%C5%82o-553x653.png","L9bqsvFj0xhs+maOhwuI9g==":"background1-5.jpg","WDveAIuOjziAofKqG3bbyA==":"008.jpg","nwhkIixqTrm9BEEV6ovwDg==":"lista_szczoteczki-861x835.png","giXY1Dgqw3av2gx5jQFxwg==":"mbr-1-1186x791.jpg","GJc6x4VkHBUiVLjHEKMS7Q==":"szczoteczka%20plus%20organizer-796x448.png","nLFlYKFJJL31omEyZ+7PkA==":"popup%20organizer%20i%20szczoteczki.gif","G7vssNMEP2i6lapAMiew+Q==":"popup%20organizer%20i%20szczoteczki.gif","P76snk98MhVAErquahxMwQ==":"popup%20organizer%20i%20szczoteczki.gif","fBYYCXZ4Axi1FOYXC+bAJQ==":"popup%20audio%20oferta.gif","wD7LEjc8Oa4Ak6W4fPn9jA==":"popup%20organizer%20i%20szczoteczki.gif","3+p8VqjSUVgOaADvsjszwg==":"sunday%20toothbrush%20popup.gif"}